text_processor_encoding/__init__.py
text_processor_encoding/preprocess_text.py
text_processor_encoding-0.0.1.dist-info/LICENSE
text_processor_encoding-0.0.1.dist-info/METADATA
text_processor_encoding-0.0.1.dist-info/WHEEL
text_processor_encoding-0.0.1.dist-info/top_level.txt
text_processor_encoding-0.0.1.dist-info/RECORD
